{
  "cand-1": {
    "name": "Meshil Maring",
    "gender": "male",
    "age": 36,
    "image": "https://i.pravatar.cc/150?u=dsmeshilmaring13@gmail.com",
    "email": "dsmeshilmaring13@gmail.com",
    "date of birth": "12/03/1989",
    "phone number": "+91 8292021380",
    "experience": "14 years",
    "job id": ["job-1", "job-3", "job-4"],
    "offer status": "Accepted",
    "hiring stage": "Resume Review",
    "interview type": "Online",
    "date applied": "15/10/2025",
    "released date": "11/10/2026",
    "joining date": "31/10/2026",
    "skills": ["React.js", "Tailwind CSS", "Node.js"],
    "applied position": "Senior Software Engineer",
    "bio": "Experienced Full Stack Developer with a passion for building scalable web applications. Expert in modern JavaScript frameworks and responsive UI design.",
    "linkedin": "https://in.linkedin.com/meshil",
    "x": "https://x.com",
    "current ctc": 20000,
    "expected ctc": 22000,
    "notice period": "20 Days",
    "location": "Gurgaon",
    "notice date": "23/11/2025",
    "resume": "https://storage.googleapis.com/resumes/meshil-maring-cv.pdf",
    "cover letter": "https://storage.googleapis.com/letters/meshil-cover-letter.docx",
    "portfolio": "https://meshil.dev/portfolio-bundle.zip",
    "follow_status": true
  },
  "cand-2": {
    "name": "Aarav Sharma",
    "gender": "female",
    "age": 34,
    "image": "https://images.unsplash.com/photo-1544005313-94ddf0286df2?q=80&w=150&h=150&auto=format&fit=crop",
    "email": "aarav.sharma@outlook.com",
    "date of birth": "12/03/1991",
    "phone number": "+91 9876543210",
    "experience": "14 years",
    "job id": ["job-1", "job-3", "job-4"],
    "offer status": "Rejected",
    "hiring stage": "Resume Review",
    "interview type": "On Call",
    "date applied": "22/11/2025",
    "released date": null,
    "joining date": "12/12/2025",
    "skills": ["Python", "Django", "PostgreSQL"],
    "applied position": "Backend Developer",
    "bio": "Backend specialist focused on architecting robust API services and database management.",
    "linkedin": "https://in.linkedin.com/aaravsharma",
    "github": "https://github.com/aarav-s",
    "current ctc": 15000,
    "expected ctc": 18500,
    "notice period": "30 Days",
    "location": "Bangalore",
    "notice date": "15/01/2026",
    "resume": "https://storage.googleapis.com/resumes/aarav-backend.pdf",
    "cover letter": null,
    "portfolio": "https://github.com/aarav-s/projects/archive/main.zip",
    "follow_status": false
  },
  "cand-3": {
    "name": "Priya Iyer",
    "gender": "female",
    "age": 35,
    "image": "https://images.unsplash.com/photo-1494790108377-be9c29b29330?q=80&w=150&h=150&auto=format&fit=crop",
    "email": "priya.iyer.dev@gmail.com",
    "date of birth": "12/03/1990",
    "phone number": "+91 9123456789",
    "experience": "14 years",
    "job id": ["job-1", "job-2", "job-3", "job-4"],
    "offer status": "Rejected",
    "hiring stage": "Resume Review",
    "interview type": "Offline",
    "date applied": "05/01/2026",
    "released date": "11/10/2026",
    "joining date": "31/10/2026",
    "skills": ["Java", "Spring Boot", "AWS"],
    "applied position": "Senior Software Engineer",
    "bio": "Cloud-native developer with expertise in enterprise Java applications.",
    "linkedin": "https://in.linkedin.com/priyaiyer",
    "link": "https://priya.dev",
    "current ctc": 25000,
    "expected ctc": 30000,
    "notice period": "Immediate",
    "location": "Hyderabad",
    "notice date": "N/A",
    "resume": "https://storage.googleapis.com/resumes/priya-iyer-cloud.pdf",
    "cover letter": "https://storage.googleapis.com/letters/priya-iyer-intro.pdf",
    "portfolio": null,
    "follow_status": false
  },
  "cand-4": {
    "name": "Rohan Verma",
    "gender": "male",
    "age": 38,
    "image": "https://images.unsplash.com/photo-1507003211169-0a1dd7228f2d?q=80&w=150&h=150&auto=format&fit=crop",
    "email": "rohan.verma88@yahoo.com",
    "date of birth": "12/03/1987",
    "phone number": "+91 8800112233",
    "experience": "14 years",
    "job id": ["job-1", "job-2", "job-3", "job-4"],
    "offer status": "Pending",
    "hiring stage": "Resume Review",
    "interview type": "On Call",
    "date applied": "12/12/2025",
    "released date": null,
    "joining date": "01/01/2026",
    "skills": ["PHP", "Laravel", "MySQL"],
    "applied position": "Web Developer",
    "bio": "Skilled Web Developer with 5 years of experience in the Laravel ecosystem.",
    "linkedin": "https://in.linkedin.com/rohanv",
    "x": "https://x.com/rohan v",
    "current ctc": 12000,
    "expected ctc": 15000,
    "notice period": "60 Days",
    "location": "Pune",
    "notice date": "01/12/2025",
    "resume": "https://storage.googleapis.com/resumes/rohan-verma.pdf",
    "cover letter": null,
    "portfolio": null,
    "follow_status": true
  },
  "cand-5": {
    "name": "Sneha Kulkarni",
    "gender": "male",
    "age": 33,
    "image": "https://images.unsplash.com/photo-1580489944761-15a19d654956?q=80&w=150&h=150&auto=format&fit=crop",
    "email": "sneha.k@techcorp.in",
    "date of birth": "12/03/1992",
    "phone number": "+91 7766554433",
    "experience": "14 years",
    "job id": ["job-1", "job-2", "job-3", "job-4"],
    "offer status": "Interviewed",
    "hiring stage": "Resume Review",
    "interview type": "Online",
    "date applied": "18/01/2026",
    "released date": null,
    "joining date": "07/02/2026",
    "skills": ["UI/UX Design", "Figma", "Adobe XD"],
    "applied position": "UI/UX Designer",
    "bio": "Creative designer dedicated to crafting user-centric digital experiences.",
    "linkedin": "https://in.linkedin.com/snehak",
    "current ctc": 18000,
    "expected ctc": 22000,
    "notice period": "15 Days",
    "location": "Mumbai",
    "notice date": "10/02/2026",
    "resume": "https://storage.googleapis.com/resumes/sneha-design.pdf",
    "cover letter": "https://storage.googleapis.com/letters/sneha-k-coverletter.pdf",
    "portfolio": "https://www.behance.net/snehak",
    "follow_status": true
  },
  "cand-6": {
    "name": "Vikram Singh",
    "gender": "female",
    "age": 42,
    "image": "https://images.unsplash.com/photo-1539571696357-5a69c17a67c6?q=80&w=150&h=150&auto=format&fit=crop",
    "email": "v.singh.eng@gmail.com",
    "date of birth": "12/03/1983",
    "phone number": "+91 9988776655",
    "experience": "14 years",
    "job id": ["job-1", "job-2", "job-3", "job-4"],
    "offer status": "Rejected",
    "hiring stage": "Resume Review",
    "interview type": "Online",
    "date applied": "30/10/2025",
    "released date": null,
    "joining date": "19/11/2025",
    "skills": ["C++", "Qt", "Embedded C"],
    "applied position": "Embedded Systems Engineer",
    "bio": "Low-level systems engineer specialized in embedded software development.",
    "linkedin": "https://in.linkedin.com/vikramsingh",
    "x": "https://x.com/vikram s",
    "current ctc": 35000,
    "expected ctc": 42000,
    "notice period": "90 Days",
    "location": "Noida",
    "notice date": "15/11/2025",
    "resume": "https://storage.googleapis.com/resumes/vikram-singh-embedded.pdf",
    "cover letter": null,
    "portfolio": null,
    "follow_status": false
  },
  "cand-7": {
    "name": "Desire Musarafu",
    "gender": "male",
    "age": 33,
    "image": "https://images.unsplash.com/photo-1580489944761-15a19d654956?q=80&w=150&h=150&auto=format&fit=crop",
    "email": "desire.musarafu@techcorp.in",
    "date of birth": "12/03/1992",
    "phone number": "+91 7766554433",
    "experience": "14 years",
    "job id": ["job-1", "job-2", "job-3", "job-4"],
    "offer status": "Interviewed",
    "hiring stage": "Resume Review",
    "interview type": "Online",
    "date applied": "18/01/2026",
    "released date": null,
    "joining date": "07/02/2026",
    "skills": ["UI/UX Design", "Figma", "Adobe XD"],
    "applied position": "UI/UX Designer",
    "bio": "Creative designer dedicated to crafting user-centric digital experiences.",
    "linkedin": "https://in.linkedin.com/snehak",
    "current ctc": 18000,
    "expected ctc": 22000,
    "notice period": "15 Days",
    "location": "Mumbai",
    "notice date": "10/02/2026",
    "resume": "https://storage.googleapis.com/resumes/sneha-design.pdf",
    "cover letter": "https://storage.googleapis.com/letters/sneha-k-coverletter.pdf",
    "portfolio": "https://www.behance.net/snehak",
    "follow_status": true
  },
  "cand-8": {
    "name": "John Doe",
    "gender": "female",
    "age": 42,
    "image": "https://images.unsplash.com/photo-1539571696357-5a69c17a67c6?q=80&w=150&h=150&auto=format&fit=crop",
    "email": "john.doe@techcorp.in",
    "date of birth": "12/03/1983",
    "phone number": "+91 9988776655",
    "experience": "14 years",
    "job id": ["job-1", "job-2", "job-3", "job-4"],
    "offer status": "Pending",
    "hiring stage": "Resume Review",
    "interview type": "Online",
    "date applied": "30/10/2025",
    "released date": "11/10/2026",
    "joining date": "31/10/2026",
    "skills": ["C++", "Qt", "Embedded C"],
    "applied position": "Senior Software Engineer",
    "bio": "Low-level systems engineer specialized in embedded software development.",
    "linkedin": "https://in.linkedin.com/vikramsingh",
    "x": "https://x.com/vikram s",
    "current ctc": 35000,
    "expected ctc": 42000,
    "notice period": "90 Days",
    "location": "Noida",
    "notice date": "15/11/2025",
    "resume": "https://storage.googleapis.com/resumes/vikram-singh-embedded.pdf",
    "cover letter": null,
    "portfolio": null,
    "follow_status": true
  }
}
